IceCertUtils/CertificateUtils.py
IceCertUtils/IceCaUtil.py
IceCertUtils/KeyToolCertificateUtils.py
IceCertUtils/OpenSSLCertificateUtils.py
IceCertUtils/PyOpenSSLCertificateUtils.py
IceCertUtils/__init__.py
zeroc_icecertutils-1.1.0.dist-info/LICENSE
zeroc_icecertutils-1.1.0.dist-info/METADATA
zeroc_icecertutils-1.1.0.dist-info/WHEEL
zeroc_icecertutils-1.1.0.dist-info/entry_points.txt
zeroc_icecertutils-1.1.0.dist-info/RECORD
