Metadata-Version: 2.1
Name: zeroc-icecertutils
Version: 1.1.0
Summary: ZeroC Ice certificate utilities
Home-page: https://github.com/zeroc-ice/icecertutils
License: BSD
Keywords: ice,certificate,ca,ssl
Author: ZeroC, Inc.
Author-email: info@zeroc.com
Requires-Python: >=3.11.0,<4.0.0
Classifier: License :: Other/Proprietary License
Classifier: Programming Language :: Python :: 3
Classifier: Programming Language :: Python :: 3.11
Classifier: Programming Language :: Python :: 3.12
Classifier: Programming Language :: Python :: 3.13
Requires-Dist: cryptography (>=43.0.0,<44.0.0)
Requires-Dist: pyopenssl (>=24.0.0,<25.0.0)
Project-URL: Repository, https://github.com/zeroc-ice/icecertutils
